LICENSE
README.md
cli/__init__.py
cli/dc_deployment.py
cli/dynamic_configuration/__init__.py
cli/dynamic_configuration/core.py
cli/dynamic_configuration/generate_schema.py
cli/dynamic_configuration/models.py
cli/dynamic_configuration/predefined_funcs.py
cli/dynamic_configuration/schema/question_schema.py
cli/dynamic_configuration/schema/questions-schema.json
cli/k8s_deployment.py
cli/releases.py
cli/scripts/authenticate-syntho-registry.sh
cli/scripts/cleanup-docker-compose.sh
cli/scripts/cleanup-kubernetes.sh
cli/scripts/compatibility-check.sh
cli/scripts/configuration-questions-dc.sh
cli/scripts/configuration-questions.sh
cli/scripts/create-offline-registry.sh
cli/scripts/deauthenticate-syntho-registry.sh
cli/scripts/deploy-kubernetes.sh
cli/scripts/deploy-ray-and-syntho-stack-dc.sh
cli/scripts/deploy-ray-and-syntho-stack.sh
cli/scripts/download-syntho-charts-release-dc.sh
cli/scripts/download-syntho-charts-release.sh
cli/scripts/get-k8s-cluster-context-name.sh
cli/scripts/k8s-deployment-preparation.sh
cli/scripts/kubectlget.sh
cli/scripts/major-pre-deployment-operations.sh
cli/scripts/package-offline-registry.sh
cli/scripts/pre-requirements-dc.sh
cli/scripts/pre-requirements-kubernetes.sh
cli/scripts/prepull-images.sh
cli/scripts/update-release.sh
cli/scripts/utils.sh
cli/scripts/validate-prepull-images-process.sh
cli/syntho_cli.py
cli/utilities/__init__.py
cli/utilities/offline_ops.py
cli/utilities/prepull_images.py
cli/utils.py
syntho_cli-1.27.3.dist-info/LICENSE
syntho_cli-1.27.3.dist-info/METADATA
syntho_cli-1.27.3.dist-info/WHEEL
syntho_cli-1.27.3.dist-info/entry_points.txt
syntho_cli-1.27.3.dist-info/RECORD
