Metadata-Version: 2.1
Name: syntho-cli
Version: 1.27.3
Summary: Syntho Stack Deployment CLI
Home-page: https://github.com/syntho-ai/deployment-tools/tree/main/cli
License: MIT
Keywords: syntho,synthetic data,deployment
Author: Syntho B.V.
Author-email: info@syntho.ai
Requires-Python: >=3.11,<4.0
Classifier: License :: OSI Approved :: MIT License
Classifier: Programming Language :: Python :: 3
Classifier: Programming Language :: Python :: 3.11
Classifier: Programming Language :: Python :: 3.12
Requires-Dist: click (>=8.1.7,<9.0.0)
Requires-Dist: datamodel-code-generator (>=0.25.7,<0.26.0)
Requires-Dist: pyyaml (>=6.0.1,<7.0.0)
Requires-Dist: requests (>=2.32.3,<3.0.0)
Requires-Dist: watchdog (>=4.0.0,<5.0.0)
Project-URL: Repository, https://github.com/syntho-ai/deployment-tools
